corolab/__init__.cpython-38-x86_64-linux-gnu.so
corolab/_version.cpython-38-x86_64-linux-gnu.so
corolab/behavior.cpython-38-x86_64-linux-gnu.so
corolab/camera.cpython-38-x86_64-linux-gnu.so
corolab/client.cpython-38-x86_64-linux-gnu.so
corolab/constants.cpython-38-x86_64-linux-gnu.so
corolab/conversions.cpython-38-x86_64-linux-gnu.so
corolab/dashboard.cpython-38-x86_64-linux-gnu.so
corolab/data.cpython-38-x86_64-linux-gnu.so
corolab/dynamics.cpython-38-x86_64-linux-gnu.so
corolab/effector.cpython-38-x86_64-linux-gnu.so
corolab/entity.cpython-38-x86_64-linux-gnu.so
corolab/fiducial.cpython-38-x86_64-linux-gnu.so
corolab/ik.cpython-38-x86_64-linux-gnu.so
corolab/item.cpython-38-x86_64-linux-gnu.so
corolab/logger.cpython-38-x86_64-linux-gnu.so
corolab/material.cpython-38-x86_64-linux-gnu.so
corolab/math.cpython-38-x86_64-linux-gnu.so
corolab/node.cpython-38-x86_64-linux-gnu.so
corolab/pose.cpython-38-x86_64-linux-gnu.so
corolab/probability.cpython-38-x86_64-linux-gnu.so
corolab/project.cpython-38-x86_64-linux-gnu.so
corolab/property.cpython-38-x86_64-linux-gnu.so
corolab/replay.cpython-38-x86_64-linux-gnu.so
corolab/robot.cpython-38-x86_64-linux-gnu.so
corolab/shape.cpython-38-x86_64-linux-gnu.so
corolab/simulator.cpython-38-x86_64-linux-gnu.so
corolab/system.cpython-38-x86_64-linux-gnu.so
corolab/task.cpython-38-x86_64-linux-gnu.so
corolab/teleoperator.cpython-38-x86_64-linux-gnu.so
corolab/tool.cpython-38-x86_64-linux-gnu.so
corolab/utils.cpython-38-x86_64-linux-gnu.so
corolab/variable.cpython-38-x86_64-linux-gnu.so
corolab/viewer.cpython-38-x86_64-linux-gnu.so
corolab/visual.cpython-38-x86_64-linux-gnu.so
corolab/workspace.cpython-38-x86_64-linux-gnu.so
corolab_app/__init__.py
corolab_app/actions.py
corolab_app/app.py
corolab_app/constants.py
corolab_app/container.py
corolab_app/content.py
corolab_app/exception.py
corolab_app/log.py
corolab_app/menu.py
corolab_app/status.py
corolab_app/editor/__init__.py
corolab_app/editor/item.py
corolab_app/editor/table.py
corolab-0.8.6.dist-info/LICENCE
corolab-0.8.6.dist-info/METADATA
corolab-0.8.6.dist-info/WHEEL
corolab-0.8.6.dist-info/entry_points.txt
corolab-0.8.6.dist-info/top_level.txt
corolab-0.8.6.dist-info/RECORD
