Metadata-Version: 2.1
Name: corolab
Version: 0.8.6
Summary: Collaborative Robotics Laboratory
Author: Parker Owan
License-File: LICENCE
Requires-Dist: numpy (==1.23.2)
Requires-Dist: transforms3d (==0.4.1)
Requires-Dist: simplejpeg (==1.6.5)
Requires-Dist: vtk (==9.2.6)
Requires-Dist: pandas (==1.5.2)
Requires-Dist: scipy (==1.10.1)
Requires-Dist: plotly (==5.11.0)
Requires-Dist: moviepy (==1.0.3)
Requires-Dist: PyQt5 (==5.15.10)
Requires-Dist: typeguard (==4.1.5)
Requires-Dist: vesper-api (==0.8.6)
